zhr_utils/__init__.py
zhr_utils/utils.py
zhr_utils-0.1.3.dist-info/LICENSE
zhr_utils-0.1.3.dist-info/METADATA
zhr_utils-0.1.3.dist-info/WHEEL
zhr_utils-0.1.3.dist-info/top_level.txt
zhr_utils-0.1.3.dist-info/RECORD
