Metadata-Version: 2.1
Name: zhr_utils
Version: 0.1.3
Summary: 常用方法库
Home-page: https://github.com/zaoheren/zhr_utils
Author: zaoheren
Author-email: zaoheren@hotmail.com
Classifier: Programming Language :: Python :: 3
Classifier: License :: OSI Approved :: MIT License
Classifier: Operating System :: OS Independent
License-File: LICENSE
